LICENSE.txt
MANIFEST.in
README.md
setup.cfg
setup.py
hft/__init__.py
hft/forecast.py
hft/metric.py
hft/optimization.py
hft/plot.py
hft/portfolio.py
hft/position.py
hft/style.json
hft/util.py
hft.egg-info/PKG-INFO
hft.egg-info/SOURCES.txt
hft.egg-info/dependency_links.txt
hft.egg-info/requires.txt
hft.egg-info/top_level.txt
hft/jar/portfolioeffect-quant-client-1.0-allinone.jar
test/__init__.py
test/credentials.ini
test/test_add_positions.py
test/test_docstring.py
test/test_forecast.py
test/test_metric_math.py
test/test_optimization.py
test/test_plot_show.py
test/test_portfolio_create.py
test/test_portfolio_metrics.py
test/test_portfolio_settings.py
test/test_position_metrics.py
test/test_scale.py