Metadata-Version: 1.1
Name: hft
Version: 1.0.4
Summary: High Frequency Portfolio Analytics by PortfolioEffect
Home-page: https://github.com/PortfolioEffect/PortfolioEffectHFT-Python
Author: Aleksey Zemnitskiy, Stephanie Toper, Andrey Kostin
Author-email: aleksey.zemnitskiy@portfolioeffect.com, stephanie.toper@portfolioeffect.com, andrey.kostin@portfolioeffect.com
License: GPL
Download-URL: https://github.com/PortfolioEffect/PortfolioEffectHFT-Python/tarball/1.0.4
Keywords: hft,trading,backtest,risk,microstructure
Platform: UNKNOWN
Classifier: Development Status :: 3 - Alpha
Classifier: Intended Audience :: Developers
Classifier: Topic :: Office/Business :: Financial :: Investment
Classifier: License :: OSI Approved :: GNU General Public License v3 (GPLv3)
Classifier: Programming Language :: Python :: 2.6
Classifier: Programming Language :: Python :: 2.7
